{
  "_format": "ethers-rs-sol-cache-3",
  "paths": {
    "artifacts": "out",
    "build_infos": "out/build-info",
    "sources": "contracts",
    "tests": "test",
    "scripts": "script",
    "libraries": [
      "lib"
    ]
  },
  "files": {
    "contracts/Building.sol": {
      "lastModificationDate": 1674970775537,
      "contentHash": "baa8c80d1b35e73ddfb6c923387e0769",
      "sourceName": "contracts/Building.sol",
      "solcConfig": {
        "settings": {
          "optimizer": {
            "enabled": true,
            "runs": 200
          },
          "metadata": {
            "bytecodeHash": "ipfs",
            "appendCBOR": true
          },
          "outputSelection": {
            "*": {
              "": [
                "ast"
              ],
              "*": [
                "abi",
                "evm.bytecode",
                "evm.deployedBytecode",
                "evm.methodIdentifiers",
                "metadata"
              ]
            }
          },
          "evmVersion": "london",
          "libraries": {}
        }
      },
      "imports": [],
      "versionRequirement": "^0.8.0",
      "artifacts": {
        "Building": {
          "0.8.10+commit.fc410830.Darwin.appleclang": "Building.sol/Building.json"
        },
        "IElevator": {
          "0.8.10+commit.fc410830.Darwin.appleclang": "Building.sol/IElevator.json"
        }
      }
    },
    "contracts/CoinFlipWrecker.sol": {
      "lastModificationDate": 1674918151232,
      "contentHash": "c45ee30494f9222b4d2d6f11b9384a2e",
      "sourceName": "contracts/CoinFlipWrecker.sol",
      "solcConfig": {
        "settings": {
          "optimizer": {
            "enabled": true,
            "runs": 200
          },
          "metadata": {
            "bytecodeHash": "ipfs",
            "appendCBOR": true
          },
          "outputSelection": {
            "*": {
              "": [
                "ast"
              ],
              "*": [
                "abi",
                "evm.bytecode",
                "evm.deployedBytecode",
                "evm.methodIdentifiers",
                "metadata"
              ]
            }
          },
          "evmVersion": "london",
          "libraries": {}
        }
      },
      "imports": [
        "interfaces/ICoinFlip.sol"
      ],
      "versionRequirement": "^0.8.0",
      "artifacts": {
        "CoinFlipWrecker": {
          "0.8.10+commit.fc410830.Darwin.appleclang": "CoinFlipWrecker.sol/CoinFlipWrecker.json"
        }
      }
    },
    "contracts/Delegation.sol": {
      "lastModificationDate": 1674922986410,
      "contentHash": "61a55e98e79821d02a0c4fa44420a161",
      "sourceName": "contracts/Delegation.sol",
      "solcConfig": {
        "settings": {
          "optimizer": {
            "enabled": true,
            "runs": 200
          },
          "metadata": {
            "bytecodeHash": "ipfs",
            "appendCBOR": true
          },
          "outputSelection": {
            "*": {
              "": [
                "ast"
              ],
              "*": [
                "abi",
                "evm.bytecode",
                "evm.deployedBytecode",
                "evm.methodIdentifiers",
                "metadata"
              ]
            }
          },
          "evmVersion": "london",
          "libraries": {}
        }
      },
      "imports": [],
      "versionRequirement": "^0.8.0",
      "artifacts": {
        "Delegate": {
          "0.8.10+commit.fc410830.Darwin.appleclang": "Delegation.sol/Delegate.json"
        },
        "Delegation": {
          "0.8.10+commit.fc410830.Darwin.appleclang": "Delegation.sol/Delegation.json"
        }
      }
    },
    "contracts/ForceWrecker.sol": {
      "lastModificationDate": 1674924067678,
      "contentHash": "9ca3ef7c286e91c7ebf4ff430ced5888",
      "sourceName": "contracts/ForceWrecker.sol",
      "solcConfig": {
        "settings": {
          "optimizer": {
            "enabled": true,
            "runs": 200
          },
          "metadata": {
            "bytecodeHash": "ipfs",
            "appendCBOR": true
          },
          "outputSelection": {
            "*": {
              "": [
                "ast"
              ],
              "*": [
                "abi",
                "evm.bytecode",
                "evm.deployedBytecode",
                "evm.methodIdentifiers",
                "metadata"
              ]
            }
          },
          "evmVersion": "london",
          "libraries": {}
        }
      },
      "imports": [],
      "versionRequirement": "^0.8.0",
      "artifacts": {
        "ForceWrecker": {
          "0.8.10+commit.fc410830.Darwin.appleclang": "ForceWrecker.sol/ForceWrecker.json"
        }
      }
    },
    "contracts/ForeverKing.sol": {
      "lastModificationDate": 1675519354105,
      "contentHash": "7a5b85ea6fa4864a545a37b0311f5646",
      "sourceName": "contracts/ForeverKing.sol",
      "solcConfig": {
        "settings": {
          "optimizer": {
            "enabled": true,
            "runs": 200
          },
          "metadata": {
            "bytecodeHash": "ipfs",
            "appendCBOR": true
          },
          "outputSelection": {
            "*": {
              "": [
                "ast"
              ],
              "*": [
                "abi",
                "evm.bytecode",
                "evm.deployedBytecode",
                "evm.methodIdentifiers",
                "metadata"
              ]
            }
          },
          "evmVersion": "london",
          "libraries": {}
        }
      },
      "imports": [],
      "versionRequirement": "^0.8.0",
      "artifacts": {
        "ForeverKing": {
          "0.8.10+commit.fc410830.Darwin.appleclang": "ForeverKing.sol/ForeverKing.json"
        }
      }
    },
    "contracts/GatekeeperOne.sol": {
      "lastModificationDate": 1675512782047,
      "contentHash": "c84db340a039721f97bb1d10445fd950",
      "sourceName": "contracts/GatekeeperOne.sol",
      "solcConfig": {
        "settings": {
          "optimizer": {
            "enabled": true,
            "runs": 200
          },
          "metadata": {
            "bytecodeHash": "ipfs",
            "appendCBOR": true
          },
          "outputSelection": {
            "*": {
              "": [
                "ast"
              ],
              "*": [
                "abi",
                "evm.bytecode",
                "evm.deployedBytecode",
                "evm.methodIdentifiers",
                "metadata"
              ]
            }
          },
          "evmVersion": "london",
          "libraries": {}
        }
      },
      "imports": [],
      "versionRequirement": "^0.8.0",
      "artifacts": {
        "GatekeeperOne": {
          "0.8.10+commit.fc410830.Darwin.appleclang": "GatekeeperOne.sol/GatekeeperOne.json"
        }
      }
    },
    "contracts/GatekeeperTwo.sol": {
      "lastModificationDate": 1675521629690,
      "contentHash": "7cd3bb3540798f2d50aa1719f70754ee",
      "sourceName": "contracts/GatekeeperTwo.sol",
      "solcConfig": {
        "settings": {
          "optimizer": {
            "enabled": true,
            "runs": 200
          },
          "metadata": {
            "bytecodeHash": "ipfs",
            "appendCBOR": true
          },
          "outputSelection": {
            "*": {
              "": [
                "ast"
              ],
              "*": [
                "abi",
                "evm.bytecode",
                "evm.deployedBytecode",
                "evm.methodIdentifiers",
                "metadata"
              ]
            }
          },
          "evmVersion": "london",
          "libraries": {}
        }
      },
      "imports": [],
      "versionRequirement": "^0.8.0",
      "artifacts": {
        "GatekeeperTwo": {
          "0.8.10+commit.fc410830.Darwin.appleclang": "GatekeeperTwo.sol/GatekeeperTwo.json"
        }
      }
    },
    "contracts/Privacy.sol": {
      "lastModificationDate": 1674956888138,
      "contentHash": "216fb9376ca282c1d603fcc3812337ec",
      "sourceName": "contracts/Privacy.sol",
      "solcConfig": {
        "settings": {
          "optimizer": {
            "enabled": true,
            "runs": 200
          },
          "metadata": {
            "bytecodeHash": "ipfs",
            "appendCBOR": true
          },
          "outputSelection": {
            "*": {
              "": [
                "ast"
              ],
              "*": [
                "abi",
                "evm.bytecode",
                "evm.deployedBytecode",
                "evm.methodIdentifiers",
                "metadata"
              ]
            }
          },
          "evmVersion": "london",
          "libraries": {}
        }
      },
      "imports": [],
      "versionRequirement": "^0.8.0",
      "artifacts": {
        "Privacy": {
          "0.8.10+commit.fc410830.Darwin.appleclang": "Privacy.sol/Privacy.json"
        }
      }
    },
    "contracts/Reentrant.sol": {
      "lastModificationDate": 1674958998113,
      "contentHash": "dd96d85c1ff01af3a66ef58bebbc12ca",
      "sourceName": "contracts/Reentrant.sol",
      "solcConfig": {
        "settings": {
          "optimizer": {
            "enabled": true,
            "runs": 200
          },
          "metadata": {
            "bytecodeHash": "ipfs",
            "appendCBOR": true
          },
          "outputSelection": {
            "*": {
              "": [
                "ast"
              ],
              "*": [
                "abi",
                "evm.bytecode",
                "evm.deployedBytecode",
                "evm.methodIdentifiers",
                "metadata"
              ]
            }
          },
          "evmVersion": "london",
          "libraries": {}
        }
      },
      "imports": [],
      "versionRequirement": "^0.8.0",
      "artifacts": {
        "IReentrance": {
          "0.8.10+commit.fc410830.Darwin.appleclang": "Reentrant.sol/IReentrance.json"
        },
        "Reentrant": {
          "0.8.10+commit.fc410830.Darwin.appleclang": "Reentrant.sol/Reentrant.json"
        }
      }
    },
    "contracts/TelephoneWrecker.sol": {
      "lastModificationDate": 1674920645652,
      "contentHash": "76c4b769ca2cea8b2dd91ab517053e9a",
      "sourceName": "contracts/TelephoneWrecker.sol",
      "solcConfig": {
        "settings": {
          "optimizer": {
            "enabled": true,
            "runs": 200
          },
          "metadata": {
            "bytecodeHash": "ipfs",
            "appendCBOR": true
          },
          "outputSelection": {
            "*": {
              "": [
                "ast"
              ],
              "*": [
                "abi",
                "evm.bytecode",
                "evm.deployedBytecode",
                "evm.methodIdentifiers",
                "metadata"
              ]
            }
          },
          "evmVersion": "london",
          "libraries": {}
        }
      },
      "imports": [
        "interfaces/ITelephone.sol"
      ],
      "versionRequirement": "^0.8.0",
      "artifacts": {
        "TelephoneWrecker": {
          "0.8.10+commit.fc410830.Darwin.appleclang": "TelephoneWrecker.sol/TelephoneWrecker.json"
        }
      }
    },
    "contracts/Trespasser1.sol": {
      "lastModificationDate": 1675513242464,
      "contentHash": "5a21e9854075e05fd1ca73f6e4ab7148",
      "sourceName": "contracts/Trespasser1.sol",
      "solcConfig": {
        "settings": {
          "optimizer": {
            "enabled": true,
            "runs": 200
          },
          "metadata": {
            "bytecodeHash": "ipfs",
            "appendCBOR": true
          },
          "outputSelection": {
            "*": {
              "": [
                "ast"
              ],
              "*": [
                "abi",
                "evm.bytecode",
                "evm.deployedBytecode",
                "evm.methodIdentifiers",
                "metadata"
              ]
            }
          },
          "evmVersion": "london",
          "libraries": {}
        }
      },
      "imports": [],
      "versionRequirement": "^0.8.0",
      "artifacts": {
        "IGatekeeperOne": {
          "0.8.10+commit.fc410830.Darwin.appleclang": "Trespasser1.sol/IGatekeeperOne.json"
        },
        "Trespasser1": {
          "0.8.10+commit.fc410830.Darwin.appleclang": "Trespasser1.sol/Trespasser1.json"
        }
      }
    },
    "contracts/Trespasser2.sol": {
      "lastModificationDate": 1675522279885,
      "contentHash": "779f9f0a08423d5083356880c22198f0",
      "sourceName": "contracts/Trespasser2.sol",
      "solcConfig": {
        "settings": {
          "optimizer": {
            "enabled": true,
            "runs": 200
          },
          "metadata": {
            "bytecodeHash": "ipfs",
            "appendCBOR": true
          },
          "outputSelection": {
            "*": {
              "": [
                "ast"
              ],
              "*": [
                "abi",
                "evm.bytecode",
                "evm.deployedBytecode",
                "evm.methodIdentifiers",
                "metadata"
              ]
            }
          },
          "evmVersion": "london",
          "libraries": {}
        }
      },
      "imports": [],
      "versionRequirement": "^0.8.0",
      "artifacts": {
        "IGatekeeperTwo": {
          "0.8.10+commit.fc410830.Darwin.appleclang": "Trespasser2.sol/IGatekeeperTwo.json"
        },
        "Trespasser2": {
          "0.8.10+commit.fc410830.Darwin.appleclang": "Trespasser2.sol/Trespasser2.json"
        }
      }
    },
    "interfaces/ICoinFlip.sol": {
      "lastModificationDate": 1674917282038,
      "contentHash": "44c0c65796a9cd5a4fa0c08485f6f634",
      "sourceName": "interfaces/ICoinFlip.sol",
      "solcConfig": {
        "settings": {
          "optimizer": {
            "enabled": true,
            "runs": 200
          },
          "metadata": {
            "bytecodeHash": "ipfs",
            "appendCBOR": true
          },
          "outputSelection": {
            "*": {
              "": [
                "ast"
              ],
              "*": [
                "abi",
                "evm.bytecode",
                "evm.deployedBytecode",
                "evm.methodIdentifiers",
                "metadata"
              ]
            }
          },
          "evmVersion": "london",
          "libraries": {}
        }
      },
      "imports": [],
      "versionRequirement": "^0.8.0",
      "artifacts": {
        "ICoinFlip": {
          "0.8.10+commit.fc410830.Darwin.appleclang": "ICoinFlip.sol/ICoinFlip.json"
        }
      }
    },
    "interfaces/ITelephone.sol": {
      "lastModificationDate": 1674920275892,
      "contentHash": "3a54770c0afa9796dd925e3471830c3a",
      "sourceName": "interfaces/ITelephone.sol",
      "solcConfig": {
        "settings": {
          "optimizer": {
            "enabled": true,
            "runs": 200
          },
          "metadata": {
            "bytecodeHash": "ipfs",
            "appendCBOR": true
          },
          "outputSelection": {
            "*": {
              "": [
                "ast"
              ],
              "*": [
                "abi",
                "evm.bytecode",
                "evm.deployedBytecode",
                "evm.methodIdentifiers",
                "metadata"
              ]
            }
          },
          "evmVersion": "london",
          "libraries": {}
        }
      },
      "imports": [],
      "versionRequirement": "^0.8.0",
      "artifacts": {
        "ITelephone": {
          "0.8.10+commit.fc410830.Darwin.appleclang": "ITelephone.sol/ITelephone.json"
        }
      }
    },
    "lib/forge-std/lib/ds-test/src/test.sol": {
      "lastModificationDate": 1675511687822,
      "contentHash": "962996f0e05d5218857a538a62d7c47e",
      "sourceName": "lib/forge-std/lib/ds-test/src/test.sol",
      "solcConfig": {
        "settings": {
          "optimizer": {
            "enabled": true,
            "runs": 200
          },
          "metadata": {
            "bytecodeHash": "ipfs",
            "appendCBOR": true
          },
          "outputSelection": {
            "*": {
              "": [
                "ast"
              ],
              "*": [
                "abi",
                "evm.bytecode",
                "evm.deployedBytecode",
                "evm.methodIdentifiers",
                "metadata"
              ]
            }
          },
          "evmVersion": "london",
          "libraries": {}
        }
      },
      "imports": [],
      "versionRequirement": ">=0.5.0",
      "artifacts": {
        "DSTest": {
          "0.8.10+commit.fc410830.Darwin.appleclang": "test.sol/DSTest.json"
        }
      }
    },
    "lib/forge-std/src/Base.sol": {
      "lastModificationDate": 1675511686290,
      "contentHash": "8f04bbbb2c16f79e14fdc321695a8ec2",
      "sourceName": "lib/forge-std/src/Base.sol",
      "solcConfig": {
        "settings": {
          "optimizer": {
            "enabled": true,
            "runs": 200
          },
          "metadata": {
            "bytecodeHash": "ipfs",
            "appendCBOR": true
          },
          "outputSelection": {
            "*": {
              "": [
                "ast"
              ],
              "*": [
                "abi",
                "evm.bytecode",
                "evm.deployedBytecode",
                "evm.methodIdentifiers",
                "metadata"
              ]
            }
          },
          "evmVersion": "london",
          "libraries": {}
        }
      },
      "imports": [
        "lib/forge-std/src/StdStorage.sol",
        "lib/forge-std/src/Vm.sol"
      ],
      "versionRequirement": ">=0.6.2, <0.9.0",
      "artifacts": {
        "CommonBase": {
          "0.8.10+commit.fc410830.Darwin.appleclang": "Base.sol/CommonBase.json"
        },
        "ScriptBase": {
          "0.8.10+commit.fc410830.Darwin.appleclang": "Base.sol/ScriptBase.json"
        },
        "TestBase": {
          "0.8.10+commit.fc410830.Darwin.appleclang": "Base.sol/TestBase.json"
        }
      }
    },
    "lib/forge-std/src/StdAssertions.sol": {
      "lastModificationDate": 1675511686290,
      "contentHash": "5bc6a90903a666d831370fa46838ed73",
      "sourceName": "lib/forge-std/src/StdAssertions.sol",
      "solcConfig": {
        "settings": {
          "optimizer": {
            "enabled": true,
            "runs": 200
          },
          "metadata": {
            "bytecodeHash": "ipfs",
            "appendCBOR": true
          },
          "outputSelection": {
            "*": {
              "": [
                "ast"
              ],
              "*": [
                "abi",
                "evm.bytecode",
                "evm.deployedBytecode",
                "evm.methodIdentifiers",
                "metadata"
              ]
            }
          },
          "evmVersion": "london",
          "libraries": {}
        }
      },
      "imports": [
        "lib/forge-std/lib/ds-test/src/test.sol",
        "lib/forge-std/src/StdMath.sol"
      ],
      "versionRequirement": ">=0.6.2, <0.9.0",
      "artifacts": {
        "StdAssertions": {
          "0.8.10+commit.fc410830.Darwin.appleclang": "StdAssertions.sol/StdAssertions.json"
        }
      }
    },
    "lib/forge-std/src/StdChains.sol": {
      "lastModificationDate": 1675511687897,
      "contentHash": "3ebb3d0e5e74705c4214d3d2255af02d",
      "sourceName": "lib/forge-std/src/StdChains.sol",
      "solcConfig": {
        "settings": {
          "optimizer": {
            "enabled": true,
            "runs": 200
          },
          "metadata": {
            "bytecodeHash": "ipfs",
            "appendCBOR": true
          },
          "outputSelection": {
            "*": {
              "": [
                "ast"
              ],
              "*": [
                "abi",
                "evm.bytecode",
                "evm.deployedBytecode",
                "evm.methodIdentifiers",
                "metadata"
              ]
            }
          },
          "evmVersion": "london",
          "libraries": {}
        }
      },
      "imports": [
        "lib/forge-std/src/Vm.sol"
      ],
      "versionRequirement": ">=0.6.2, <0.9.0",
      "artifacts": {
        "StdChains": {
          "0.8.10+commit.fc410830.Darwin.appleclang": "StdChains.sol/StdChains.json"
        }
      }
    },
    "lib/forge-std/src/StdCheats.sol": {
      "lastModificationDate": 1675511687897,
      "contentHash": "ed0130ab99d0859cf7da2949203a4679",
      "sourceName": "lib/forge-std/src/StdCheats.sol",
      "solcConfig": {
        "settings": {
          "optimizer": {
            "enabled": true,
            "runs": 200
          },
          "metadata": {
            "bytecodeHash": "ipfs",
            "appendCBOR": true
          },
          "outputSelection": {
            "*": {
              "": [
                "ast"
              ],
              "*": [
                "abi",
                "evm.bytecode",
                "evm.deployedBytecode",
                "evm.methodIdentifiers",
                "metadata"
              ]
            }
          },
          "evmVersion": "london",
          "libraries": {}
        }
      },
      "imports": [
        "lib/forge-std/src/StdStorage.sol",
        "lib/forge-std/src/Vm.sol"
      ],
      "versionRequirement": ">=0.6.2, <0.9.0",
      "artifacts": {
        "StdCheats": {
          "0.8.10+commit.fc410830.Darwin.appleclang": "StdCheats.sol/StdCheats.json"
        },
        "StdCheatsSafe": {
          "0.8.10+commit.fc410830.Darwin.appleclang": "StdCheats.sol/StdCheatsSafe.json"
        }
      }
    },
    "lib/forge-std/src/StdError.sol": {
      "lastModificationDate": 1675511686291,
      "contentHash": "64c896e1276a291776e5ea5aecb3870a",
      "sourceName": "lib/forge-std/src/StdError.sol",
      "solcConfig": {
        "settings": {
          "optimizer": {
            "enabled": true,
            "runs": 200
          },
          "metadata": {
            "bytecodeHash": "ipfs",
            "appendCBOR": true
          },
          "outputSelection": {
            "*": {
              "": [
                "ast"
              ],
              "*": [
                "abi",
                "evm.bytecode",
                "evm.deployedBytecode",
                "evm.methodIdentifiers",
                "metadata"
              ]
            }
          },
          "evmVersion": "london",
          "libraries": {}
        }
      },
      "imports": [],
      "versionRequirement": ">=0.6.2, <0.9.0",
      "artifacts": {
        "stdError": {
          "0.8.10+commit.fc410830.Darwin.appleclang": "StdError.sol/stdError.json"
        }
      }
    },
    "lib/forge-std/src/StdJson.sol": {
      "lastModificationDate": 1675511686291,
      "contentHash": "016de2d7ee55960094cc97ec792025bb",
      "sourceName": "lib/forge-std/src/StdJson.sol",
      "solcConfig": {
        "settings": {
          "optimizer": {
            "enabled": true,
            "runs": 200
          },
          "metadata": {
            "bytecodeHash": "ipfs",
            "appendCBOR": true
          },
          "outputSelection": {
            "*": {
              "": [
                "ast"
              ],
              "*": [
                "abi",
                "evm.bytecode",
                "evm.deployedBytecode",
                "evm.methodIdentifiers",
                "metadata"
              ]
            }
          },
          "evmVersion": "london",
          "libraries": {}
        }
      },
      "imports": [
        "lib/forge-std/src/Vm.sol"
      ],
      "versionRequirement": ">=0.6.0, <0.9.0",
      "artifacts": {
        "stdJson": {
          "0.8.10+commit.fc410830.Darwin.appleclang": "StdJson.sol/stdJson.json"
        }
      }
    },
    "lib/forge-std/src/StdMath.sol": {
      "lastModificationDate": 1675511686291,
      "contentHash": "9da8f453eba6bb98f3d75bc6822bfb29",
      "sourceName": "lib/forge-std/src/StdMath.sol",
      "solcConfig": {
        "settings": {
          "optimizer": {
            "enabled": true,
            "runs": 200
          },
          "metadata": {
            "bytecodeHash": "ipfs",
            "appendCBOR": true
          },
          "outputSelection": {
            "*": {
              "": [
                "ast"
              ],
              "*": [
                "abi",
                "evm.bytecode",
                "evm.deployedBytecode",
                "evm.methodIdentifiers",
                "metadata"
              ]
            }
          },
          "evmVersion": "london",
          "libraries": {}
        }
      },
      "imports": [],
      "versionRequirement": ">=0.6.2, <0.9.0",
      "artifacts": {
        "stdMath": {
          "0.8.10+commit.fc410830.Darwin.appleclang": "StdMath.sol/stdMath.json"
        }
      }
    },
    "lib/forge-std/src/StdStorage.sol": {
      "lastModificationDate": 1675511686291,
      "contentHash": "3cb9868082df39a53927db09dbc21f23",
      "sourceName": "lib/forge-std/src/StdStorage.sol",
      "solcConfig": {
        "settings": {
          "optimizer": {
            "enabled": true,
            "runs": 200
          },
          "metadata": {
            "bytecodeHash": "ipfs",
            "appendCBOR": true
          },
          "outputSelection": {
            "*": {
              "": [
                "ast"
              ],
              "*": [
                "abi",
                "evm.bytecode",
                "evm.deployedBytecode",
                "evm.methodIdentifiers",
                "metadata"
              ]
            }
          },
          "evmVersion": "london",
          "libraries": {}
        }
      },
      "imports": [
        "lib/forge-std/src/Vm.sol"
      ],
      "versionRequirement": ">=0.6.2, <0.9.0",
      "artifacts": {
        "stdStorage": {
          "0.8.10+commit.fc410830.Darwin.appleclang": "StdStorage.sol/stdStorage.json"
        },
        "stdStorageSafe": {
          "0.8.10+commit.fc410830.Darwin.appleclang": "StdStorage.sol/stdStorageSafe.json"
        }
      }
    },
    "lib/forge-std/src/StdUtils.sol": {
      "lastModificationDate": 1675511687898,
      "contentHash": "7e77cc909faa708c1511911ca74c497e",
      "sourceName": "lib/forge-std/src/StdUtils.sol",
      "solcConfig": {
        "settings": {
          "optimizer": {
            "enabled": true,
            "runs": 200
          },
          "metadata": {
            "bytecodeHash": "ipfs",
            "appendCBOR": true
          },
          "outputSelection": {
            "*": {
              "": [
                "ast"
              ],
              "*": [
                "abi",
                "evm.bytecode",
                "evm.deployedBytecode",
                "evm.methodIdentifiers",
                "metadata"
              ]
            }
          },
          "evmVersion": "london",
          "libraries": {}
        }
      },
      "imports": [
        "lib/forge-std/src/Vm.sol",
        "lib/forge-std/src/interfaces/IMulticall3.sol"
      ],
      "versionRequirement": ">=0.6.2, <0.9.0",
      "artifacts": {
        "StdUtils": {
          "0.8.10+commit.fc410830.Darwin.appleclang": "StdUtils.sol/StdUtils.json"
        }
      }
    },
    "lib/forge-std/src/Test.sol": {
      "lastModificationDate": 1675511686292,
      "contentHash": "9ca73393dbc2f8cde2aa628f8d05c5d5",
      "sourceName": "lib/forge-std/src/Test.sol",
      "solcConfig": {
        "settings": {
          "optimizer": {
            "enabled": true,
            "runs": 200
          },
          "metadata": {
            "bytecodeHash": "ipfs",
            "appendCBOR": true
          },
          "outputSelection": {
            "*": {
              "": [
                "ast"
              ],
              "*": [
                "abi",
                "evm.bytecode",
                "evm.deployedBytecode",
                "evm.methodIdentifiers",
                "metadata"
              ]
            }
          },
          "evmVersion": "london",
          "libraries": {}
        }
      },
      "imports": [
        "lib/forge-std/lib/ds-test/src/test.sol",
        "lib/forge-std/src/Base.sol",
        "lib/forge-std/src/StdAssertions.sol",
        "lib/forge-std/src/StdChains.sol",
        "lib/forge-std/src/StdCheats.sol",
        "lib/forge-std/src/StdError.sol",
        "lib/forge-std/src/StdJson.sol",
        "lib/forge-std/src/StdMath.sol",
        "lib/forge-std/src/StdStorage.sol",
        "lib/forge-std/src/StdUtils.sol",
        "lib/forge-std/src/Vm.sol",
        "lib/forge-std/src/console.sol",
        "lib/forge-std/src/console2.sol",
        "lib/forge-std/src/interfaces/IMulticall3.sol"
      ],
      "versionRequirement": ">=0.6.2, <0.9.0",
      "artifacts": {
        "Test": {
          "0.8.10+commit.fc410830.Darwin.appleclang": "Test.sol/Test.json"
        }
      }
    },
    "lib/forge-std/src/Vm.sol": {
      "lastModificationDate": 1675511686292,
      "contentHash": "86d01713430fa0877970a6ed8f99dc78",
      "sourceName": "lib/forge-std/src/Vm.sol",
      "solcConfig": {
        "settings": {
          "optimizer": {
            "enabled": true,
            "runs": 200
          },
          "metadata": {
            "bytecodeHash": "ipfs",
            "appendCBOR": true
          },
          "outputSelection": {
            "*": {
              "": [
                "ast"
              ],
              "*": [
                "abi",
                "evm.bytecode",
                "evm.deployedBytecode",
                "evm.methodIdentifiers",
                "metadata"
              ]
            }
          },
          "evmVersion": "london",
          "libraries": {}
        }
      },
      "imports": [],
      "versionRequirement": ">=0.6.2, <0.9.0",
      "artifacts": {
        "Vm": {
          "0.8.10+commit.fc410830.Darwin.appleclang": "Vm.sol/Vm.json"
        },
        "VmSafe": {
          "0.8.10+commit.fc410830.Darwin.appleclang": "Vm.sol/VmSafe.json"
        }
      }
    },
    "lib/forge-std/src/console.sol": {
      "lastModificationDate": 1675511686292,
      "contentHash": "100b8a33b917da1147740d7ab8b0ded3",
      "sourceName": "lib/forge-std/src/console.sol",
      "solcConfig": {
        "settings": {
          "optimizer": {
            "enabled": true,
            "runs": 200
          },
          "metadata": {
            "bytecodeHash": "ipfs",
            "appendCBOR": true
          },
          "outputSelection": {
            "*": {
              "": [
                "ast"
              ],
              "*": [
                "abi",
                "evm.bytecode",
                "evm.deployedBytecode",
                "evm.methodIdentifiers",
                "metadata"
              ]
            }
          },
          "evmVersion": "london",
          "libraries": {}
        }
      },
      "imports": [],
      "versionRequirement": ">=0.4.22, <0.9.0",
      "artifacts": {
        "console": {
          "0.8.10+commit.fc410830.Darwin.appleclang": "console.sol/console.json"
        }
      }
    },
    "lib/forge-std/src/console2.sol": {
      "lastModificationDate": 1675511686292,
      "contentHash": "2096b4e5f252c5df9909cccbe3d2da2e",
      "sourceName": "lib/forge-std/src/console2.sol",
      "solcConfig": {
        "settings": {
          "optimizer": {
            "enabled": true,
            "runs": 200
          },
          "metadata": {
            "bytecodeHash": "ipfs",
            "appendCBOR": true
          },
          "outputSelection": {
            "*": {
              "": [
                "ast"
              ],
              "*": [
                "abi",
                "evm.bytecode",
                "evm.deployedBytecode",
                "evm.methodIdentifiers",
                "metadata"
              ]
            }
          },
          "evmVersion": "london",
          "libraries": {}
        }
      },
      "imports": [],
      "versionRequirement": ">=0.4.22, <0.9.0",
      "artifacts": {
        "console2": {
          "0.8.10+commit.fc410830.Darwin.appleclang": "console2.sol/console2.json"
        }
      }
    },
    "lib/forge-std/src/interfaces/IMulticall3.sol": {
      "lastModificationDate": 1675511686293,
      "contentHash": "7b131ca1ca32ef6378b7b9ad5488b901",
      "sourceName": "lib/forge-std/src/interfaces/IMulticall3.sol",
      "solcConfig": {
        "settings": {
          "optimizer": {
            "enabled": true,
            "runs": 200
          },
          "metadata": {
            "bytecodeHash": "ipfs",
            "appendCBOR": true
          },
          "outputSelection": {
            "*": {
              "": [
                "ast"
              ],
              "*": [
                "abi",
                "evm.bytecode",
                "evm.deployedBytecode",
                "evm.methodIdentifiers",
                "metadata"
              ]
            }
          },
          "evmVersion": "london",
          "libraries": {}
        }
      },
      "imports": [],
      "versionRequirement": ">=0.6.2, <0.9.0",
      "artifacts": {
        "IMulticall3": {
          "0.8.10+commit.fc410830.Darwin.appleclang": "IMulticall3.sol/IMulticall3.json"
        }
      }
    },
    "test/Trespasser1.t.sol": {
      "lastModificationDate": 1675513441225,
      "contentHash": "147e222da0682d209b2d2d64cdab4309",
      "sourceName": "test/Trespasser1.t.sol",
      "solcConfig": {
        "settings": {
          "optimizer": {
            "enabled": true,
            "runs": 200
          },
          "metadata": {
            "bytecodeHash": "ipfs",
            "appendCBOR": true
          },
          "outputSelection": {
            "*": {
              "": [
                "ast"
              ],
              "*": [
                "abi",
                "evm.bytecode",
                "evm.deployedBytecode",
                "evm.methodIdentifiers",
                "metadata"
              ]
            }
          },
          "evmVersion": "london",
          "libraries": {}
        }
      },
      "imports": [
        "contracts/GatekeeperOne.sol",
        "contracts/Trespasser1.sol",
        "lib/forge-std/lib/ds-test/src/test.sol",
        "lib/forge-std/src/Base.sol",
        "lib/forge-std/src/StdAssertions.sol",
        "lib/forge-std/src/StdChains.sol",
        "lib/forge-std/src/StdCheats.sol",
        "lib/forge-std/src/StdError.sol",
        "lib/forge-std/src/StdJson.sol",
        "lib/forge-std/src/StdMath.sol",
        "lib/forge-std/src/StdStorage.sol",
        "lib/forge-std/src/StdUtils.sol",
        "lib/forge-std/src/Test.sol",
        "lib/forge-std/src/Vm.sol",
        "lib/forge-std/src/console.sol",
        "lib/forge-std/src/console2.sol",
        "lib/forge-std/src/interfaces/IMulticall3.sol"
      ],
      "versionRequirement": "^0.8.0",
      "artifacts": {
        "Trespasser1Test": {
          "0.8.10+commit.fc410830.Darwin.appleclang": "Trespasser1.t.sol/Trespasser1Test.json"
        }
      }
    },
    "test/Trespasser2.t.sol": {
      "lastModificationDate": 1675522251048,
      "contentHash": "4f853012aaa4ce06ffef153af1d5ebfe",
      "sourceName": "test/Trespasser2.t.sol",
      "solcConfig": {
        "settings": {
          "optimizer": {
            "enabled": true,
            "runs": 200
          },
          "metadata": {
            "bytecodeHash": "ipfs",
            "appendCBOR": true
          },
          "outputSelection": {
            "*": {
              "": [
                "ast"
              ],
              "*": [
                "abi",
                "evm.bytecode",
                "evm.deployedBytecode",
                "evm.methodIdentifiers",
                "metadata"
              ]
            }
          },
          "evmVersion": "london",
          "libraries": {}
        }
      },
      "imports": [
        "contracts/GatekeeperTwo.sol",
        "contracts/Trespasser2.sol",
        "lib/forge-std/lib/ds-test/src/test.sol",
        "lib/forge-std/src/Base.sol",
        "lib/forge-std/src/StdAssertions.sol",
        "lib/forge-std/src/StdChains.sol",
        "lib/forge-std/src/StdCheats.sol",
        "lib/forge-std/src/StdError.sol",
        "lib/forge-std/src/StdJson.sol",
        "lib/forge-std/src/StdMath.sol",
        "lib/forge-std/src/StdStorage.sol",
        "lib/forge-std/src/StdUtils.sol",
        "lib/forge-std/src/Test.sol",
        "lib/forge-std/src/Vm.sol",
        "lib/forge-std/src/console.sol",
        "lib/forge-std/src/console2.sol",
        "lib/forge-std/src/interfaces/IMulticall3.sol"
      ],
      "versionRequirement": "^0.8.0",
      "artifacts": {
        "Trespasser1Test": {
          "0.8.10+commit.fc410830.Darwin.appleclang": "Trespasser2.t.sol/Trespasser1Test.json"
        }
      }
    }
  }
}